{
  "type": "FeatureCollection",
  "features": [
    {
      "type": "Feature",
      "properties": {
        "stroke": "#7275d5",
        "stroke-width": 2,
        "stroke-opacity": 1,
        "fill": "#7275d5",
        "fill-opacity": 0.5,
        "id": "golf-club-milano"
      },
      "geometry": {
        "type": "Polygon",
        "coordinates": [
          [
            [9.291515350341797, 45.62199182387297],
            [9.291729927062987, 45.62043104700609],
            [9.29366111755371, 45.62007086155889],
            [9.294905662536621, 45.62088127556128],
            [9.29443359375, 45.622321982642525],
            [9.291515350341797, 45.62199182387297]
          ]
        ]
      }
    },
    {
      "type": "Feature",
      "properties": {
        "stroke": "#7275d5",
        "stroke-width": 2,
        "stroke-opacity": 1,
        "fill": "#7275d5",
        "fill-opacity": 0.5,
        "id": "parco-di-villa-litta"
      },
      "geometry": {
        "type": "Polygon",
        "coordinates": [
          [
            [9.27495002746582, 45.61727934588936],
            [9.275078773498535, 45.615118077021705],
            [9.27769660949707, 45.615328204039415],
            [9.278554916381836, 45.616919140196046],
            [9.27743911743164, 45.6180297669855],
            [9.27495002746582, 45.61727934588936]
          ]
        ]
      }
    },
    {
      "type": "Feature",
      "properties": {
        "stroke": "#7275d5",
        "stroke-width": 2,
        "stroke-opacity": 1,
        "fill": "#7275d5",
        "fill-opacity": 0.5,
        "id": "bosco-bello"
      },
      "geometry": {
        "type": "Polygon",
        "coordinates": [
          [
            [9.287266731262207, 45.62691398938987],
            [9.291043281555176, 45.62691398938987],
            [9.291043281555176, 45.62877469548665],
            [9.287266731262207, 45.62877469548665],
            [9.287266731262207, 45.62691398938987]
          ]
        ]
      }
    },
    {
      "type": "Feature",
      "properties": {
        "stroke": "#7275d5",
        "stroke-width": 2,
        "stroke-opacity": 1,
        "fill": "#7275d5",
        "fill-opacity": 0.5,
        "id": "st-georges-premier"
      },
      "geometry": {
        "type": "Polygon",
        "coordinates": [
          [
            [9.289369583129883, 45.607462913183],
            [9.289755821228027, 45.60617193946742],
            [9.291772842407225, 45.60611189345524],
            [9.292545318603516, 45.6072527566958],
            [9.292116165161133, 45.6083035312583],
            [9.290399551391602, 45.6083035312583],
            [9.289369583129883, 45.607462913183]
          ]
        ]
      }
    }
  ]
}
